src/__init__.py
src/__main__.py
src/adapters/__init__.py
src/adapters/git_provider.py
src/adapters/mcp_tools.py
src/adapters/prompts.py
src/domain/__init__.py
src/domain/models.py
src/infrastructure/__init__.py
src/usecases/__init__.py
src/usecases/image_checker.py
src/usecases/latex_scanner.py
src/usecases/toc_aligner.py
doc_reviewer_mcp-0.2.1.dist-info/METADATA
doc_reviewer_mcp-0.2.1.dist-info/WHEEL
doc_reviewer_mcp-0.2.1.dist-info/entry_points.txt
doc_reviewer_mcp-0.2.1.dist-info/licenses/LICENSE
doc_reviewer_mcp-0.2.1.dist-info/RECORD
