Metadata-Version: 2.4
Name: doc-reviewer-mcp
Version: 0.2.1
Summary: MCP server for OCR-generated Markdown document review and diagnostics
Author-email: LiHtCocoa <1051293382@qq.com>
License-Expression: MIT
License-File: LICENSE
Keywords: diagnostics,document-review,markdown,mcp,ocr
Classifier: Development Status :: 3 - Alpha
Classifier: Intended Audience :: Developers
Classifier: License :: OSI Approved :: MIT License
Classifier: Programming Language :: Python :: 3
Classifier: Programming Language :: Python :: 3.10
Classifier: Programming Language :: Python :: 3.11
Classifier: Programming Language :: Python :: 3.12
Requires-Python: >=3.10
Requires-Dist: fastmcp>=0.4.0
Requires-Dist: gitpython>=3.1.0
Requires-Dist: marko>=2.0.0
Requires-Dist: mcp[cli]>=1.0.0
Requires-Dist: pydantic>=2.0.0
Requires-Dist: rapidfuzz>=3.0.0
